bempp_rs-0.2.0.dist-info/METADATA
bempp_rs-0.2.0.dist-info/WHEEL
bempp_rs-0.2.0.dist-info/licenses/LICENSE
bempp.libs/libblas-fe34f726.so.3
bempp.libs/liblapack-31d7d384.so.3
bempp.libs/libquadmath-776d53b6.so.0
bempp.libs/libgfortran-93980b03.so.5
bempp/__init__.py
bempp/assembly/potential.py
bempp/assembly/boundary.py
bempp/assembly/__init__.py
bempp/function_space.py
bempp/_bempprs/__init__.py
bempp/_bempprs/ffi.py
bempp/_bempprs/_bempprs.so
bempp_rs-0.2.0.dist-info/RECORD
