Metadata-Version: 2.3
Name: bempp-rs
Version: 0.2.0
Classifier: Programming Language :: Rust
Classifier: Programming Language :: Python :: Implementation :: CPython
Requires-Dist: maturin >=1.7
Requires-Dist: numpy
Requires-Dist: scipy
Requires-Dist: cffi
Requires-Dist: patchelf ; platform_system == 'Linux'
Requires-Dist: ndelement
Requires-Dist: ndgrid
License-File: LICENSE
Summary: Boundary element method library
Keywords: numerics
Home-Page: https://github.com/bempp/bempp-rs
Author: Timo Betcke <timo.betcke@gmail.com>, Srinath Kailasa <srinathkailasa@gmail.com>, Matthew Scroggs <rust@mscroggs.co.uk>
Author-email: Timo Betcke <timo.betcke@gmail.com>, Srinath Kailasa <srinathkailasa@gmail.com>, Matthew Scroggs <rust@mscroggs.co.uk>
License: BSD-3-Clause
Requires-Python: >=3.8
Project-URL: homepage, https://github.com/bempp/bempp-rs
Project-URL: repository, https://github.com/bempp/bempp-rs
